{
  "patient": [
    {
      "name": "Olivia Rodrigo",
      "age": 20,
      "telephone": 64984632514,
      "email": "olivia@gmail.com",
      "id": 1
    },
    {
      "name": "Joshua Basset",
      "age": 23,
      "telephone": 64999868583,
      "email": "joshua@gmail.com",
      "id": 2
    },
    {
      "name": "Sabrina Carpenter",
      "age": 22,
      "telephone": 64984563625,
      "email": "sabrina@gmail.com",
      "id": 3
    },
    {
      "name": "Damon Salvatore",
      "age": 89,
      "telephone": 64996352147,
      "email": "damon@gmail.com",
      "id": 4
    },
    {
      "name": "Stephan Salvatore",
      "age": 90,
      "telephone": 64995896321,
      "email": "stephan@gmail.com",
      "id": 5
    },
    {
      "name": "Klaus Mikelson",
      "age": 99,
      "telephone": 64995874563,
      "email": "klaus@gmail.com",
      "id": 6
    },
    {
      "name": "Jeremy Gilbert",
      "age": 17,
      "telephone": 64845632145,
      "email": "jeremygilbert@gmail.com",
      "id": 7
    }
  ],
  "doctor": [
    {
      "name": "Doctor Ray",
      "crm": 57451,
      "specialization": "Cirurgião Plástico",
      "id": 1
    },
    {
      "name": "Doctor House",
      "crm": 36589,
      "specialization": "Infectologista",
      "id": 2
    },
    {
      "name": "Taylor Swift",
      "crm": 23654,
      "specialization": "Neurologista",
      "id": 3
    },
    {
      "name": "Meredith Grey",
      "crm": 89654,
      "specialization": "Cardiologista",
      "id": 4
    },
    {
      "name": "Katherine Petrova",
      "crm": 54698,
      "specialization": "Psiquiatra",
      "id": 5
    }
  ],
  "appointment": [
    {
      "doctorID": 2,
      "patientID": 2,
      "date": "2023-08-16T19:00:00.000Z",
      "symptoms": "dfkjgnbfmng dfgbijndfjk fkgjbndf",
      "id": 1
    },
    {
      "doctorID": 3,
      "patientID": 1,
      "date": "2023-08-21T20:00:00.000Z",
      "symptoms": "corna",
      "id": 2
    },
    {
      "doctorID": 4,
      "patientID": 3,
      "date": "2023-08-24T17:00:00.000Z",
      "symptoms": "sfdgb etyhnedty n rdghjety",
      "id": 3
    },
    {
      "doctorID": 3,
      "patientID": 3,
      "date": "2023-08-24T16:00:00.000Z",
      "symptoms": "adrvfadrf aedrgrhrty",
      "id": 4
    },
    {
      "doctorID": 1,
      "patientID": 1,
      "date": "2023-08-30T12:00:00.000Z",
      "symptoms": "okjmuhi ygvbyuhbn",
      "id": 5
    },
    {
      "doctorID": 1,
      "patientID": 2,
      "date": "2023-08-29T13:00:00.000Z",
      "symptoms": "dtujryk ketyun wrthw wryhjstr",
      "id": 6
    }
  ]
}